{
    "1": {
        "bandwidth_bytes": "318700162",
        "blocksize": "524288",
        "io_bytes": "28694806528",
        "iops": "607.872319",
        "latency": "1639933.787049",
        "number_of_jobs": "1",
        "runtime_seconds": "90",
        "std_deviation": "22441730.481634002",
        "total_ios": "54731"
    },
    "12": {
        "bandwidth_bytes": "7791409819.0",
        "blocksize": "524288",
        "io_bytes": "701234675712.0",
        "iops": "14860.934878999997",
        "latency": "798750.3063210673",
        "number_of_jobs": "1",
        "runtime_seconds": "90",
        "std_deviation": "261358.09589818167",
        "total_ios": "1337499"
    },
    "16": {
        "bandwidth_bytes": "9110917370.0",
        "blocksize": "524288",
        "io_bytes": "819991674880.0",
        "iops": "17377.695804",
        "latency": "910464.6966676594",
        "number_of_jobs": "1",
        "runtime_seconds": "90",
        "std_deviation": "244224.74105071882",
        "total_ios": "1564010"
    },
    "2": {
        "bandwidth_bytes": "1303511119.0",
        "blocksize": "524288",
        "io_bytes": "117317304320.0",
        "iops": "2486.250153",
        "latency": "800153.9910085619",
        "number_of_jobs": "1",
        "runtime_seconds": "90",
        "std_deviation": "8181423.119200475",
        "total_ios": "223765"
    },
    "20": {
        "bandwidth_bytes": "9891184520.0",
        "blocksize": "524288",
        "io_bytes": "890217431040.0",
        "iops": "18865.892843",
        "latency": "1049624.832640434",
        "number_of_jobs": "1",
        "runtime_seconds": "90",
        "std_deviation": "305703.992796516",
        "total_ios": "1697951"
    },
    "24": {
        "bandwidth_bytes": "10371831440.0",
        "blocksize": "524288",
        "io_bytes": "933476958208.0",
        "iops": "19782.609644999997",
        "latency": "1202182.7853696235",
        "number_of_jobs": "1",
        "runtime_seconds": "90",
        "std_deviation": "431830.1492257024",
        "total_ios": "1780458"
    },
    "3": {
        "bandwidth_bytes": "2655453379.0",
        "blocksize": "524288",
        "io_bytes": "239053832192.0",
        "iops": "5064.875373",
        "latency": "587951.152131958",
        "number_of_jobs": "1",
        "runtime_seconds": "90",
        "std_deviation": "1776995.1992032796",
        "total_ios": "455959"
    },
    "32": {
        "bandwidth_bytes": "10859640235.0",
        "blocksize": "524288",
        "io_bytes": "977381883904.0",
        "iops": "20712.942196",
        "latency": "1533044.70305838",
        "number_of_jobs": "1",
        "runtime_seconds": "90",
        "std_deviation": "623779.2669404177",
        "total_ios": "1864192"
    },
    "4": {
        "bandwidth_bytes": "3528652047.0",
        "blocksize": "524288",
        "io_bytes": "317582213120.0",
        "iops": "6730.3696629999995",
        "latency": "589593.1046786713",
        "number_of_jobs": "1",
        "runtime_seconds": "90",
        "std_deviation": "545029.5373640758",
        "total_ios": "605740"
    },
    "6": {
        "bandwidth_bytes": "4879103898.0",
        "blocksize": "524288",
        "io_bytes": "439124230144.0",
        "iops": "9306.152154",
        "latency": "638988.4193857725",
        "number_of_jobs": "1",
        "runtime_seconds": "90",
        "std_deviation": "403159.6423580878",
        "total_ios": "837563"
    },
    "8": {
        "bandwidth_bytes": "6015543763.0",
        "blocksize": "524288",
        "io_bytes": "541404954624.0",
        "iops": "11473.739180999999",
        "latency": "690449.5154031846",
        "number_of_jobs": "1",
        "runtime_seconds": "90",
        "std_deviation": "368606.45880863763",
        "total_ios": "1032648"
    },
    "latency_at_max_bandwidth": "1.53304470305838",
    "latency_at_max_iops": "1.53304470305838",
    "maximum_bandwidth": "10859640235.0",
    "maximum_iops": "20712.942196"
}