{
    "1": {
        "bandwidth_bytes": "1521415555.0",
        "blocksize": "524288",
        "io_bytes": "136929869824.0",
        "iops": "2901.8698869999994",
        "latency": "2747745.0727793262",
        "number_of_jobs": "1",
        "runtime_seconds": "90",
        "std_deviation": "849257.8815376264",
        "total_ios": "261173"
    },
    "10": {
        "bandwidth_bytes": "1594396938.0",
        "blocksize": "524288",
        "io_bytes": "143533801472.0",
        "iops": "3040.271041",
        "latency": "26301482.27791384",
        "number_of_jobs": "1",
        "runtime_seconds": "90",
        "std_deviation": "28234034.479459226",
        "total_ios": "273697"
    },
    "11": {
        "bandwidth_bytes": "1593283181.0",
        "blocksize": "524288",
        "io_bytes": "143433138176.0",
        "iops": "3038.057848",
        "latency": "28955482.096665323",
        "number_of_jobs": "1",
        "runtime_seconds": "90",
        "std_deviation": "33237183.059808306",
        "total_ios": "273497"
    },
    "2": {
        "bandwidth_bytes": "1550534627.0",
        "blocksize": "524288",
        "io_bytes": "139553931264.0",
        "iops": "2957.3212239999993",
        "latency": "5400571.875770047",
        "number_of_jobs": "1",
        "runtime_seconds": "90",
        "std_deviation": "2532486.0304622957",
        "total_ios": "266170"
    },
    "3": {
        "bandwidth_bytes": "1567857467.0",
        "blocksize": "524288",
        "io_bytes": "141114212352.0",
        "iops": "2990.2730369999995",
        "latency": "8016049.915222891",
        "number_of_jobs": "1",
        "runtime_seconds": "90",
        "std_deviation": "4735178.751247389",
        "total_ios": "269138"
    },
    "4": {
        "bandwidth_bytes": "1572757541.0",
        "blocksize": "524288",
        "io_bytes": "141558808576.0",
        "iops": "2999.5303069999995",
        "latency": "10658341.187531099",
        "number_of_jobs": "1",
        "runtime_seconds": "90",
        "std_deviation": "7197579.849851571",
        "total_ios": "269978"
    },
    "5": {
        "bandwidth_bytes": "1581160650.0",
        "blocksize": "524288",
        "io_bytes": "142321647616.0",
        "iops": "3015.469101",
        "latency": "13253974.841778737",
        "number_of_jobs": "1",
        "runtime_seconds": "90",
        "std_deviation": "10036107.247387428",
        "total_ios": "271425"
    },
    "6": {
        "bandwidth_bytes": "1584029452.0",
        "blocksize": "524288",
        "io_bytes": "142577500160.0",
        "iops": "3020.8520210000006",
        "latency": "15878845.758967765",
        "number_of_jobs": "1",
        "runtime_seconds": "90",
        "std_deviation": "13162852.137043858",
        "total_ios": "271905"
    },
    "7": {
        "bandwidth_bytes": "1586644489.0",
        "blocksize": "524288",
        "io_bytes": "142821818368.0",
        "iops": "3025.750962",
        "latency": "18497132.054897614",
        "number_of_jobs": "1",
        "runtime_seconds": "90",
        "std_deviation": "16230004.346922733",
        "total_ios": "272363"
    },
    "8": {
        "bandwidth_bytes": "1588427124.0",
        "blocksize": "524288",
        "io_bytes": "142987493376.0",
        "iops": "3029.062216",
        "latency": "21117370.532803018",
        "number_of_jobs": "1",
        "runtime_seconds": "90",
        "std_deviation": "20070956.070935648",
        "total_ios": "272671"
    },
    "9": {
        "bandwidth_bytes": "1591810856.0",
        "blocksize": "524288",
        "io_bytes": "143290531840.0",
        "iops": "3035.427291",
        "latency": "23708778.109991457",
        "number_of_jobs": "1",
        "runtime_seconds": "90",
        "std_deviation": "24472767.302159794",
        "total_ios": "273241"
    },
    "latency_at_max_bandwidth": "26.301482277913838",
    "latency_at_max_iops": "26.301482277913838",
    "maximum_bandwidth": "1594396938.0",
    "maximum_iops": "3040.271041"
}