{
    "12": {
        "bandwidth_bytes": "97779738",
        "blocksize": "16384",
        "io_bytes": "5867077632",
        "iops": "5967.818276",
        "latency": "2006660.792719",
        "number_of_jobs": "1",
        "runtime_seconds": "60",
        "std_deviation": "799909.1877600001",
        "total_ios": "358087"
    },
    "128": {
        "bandwidth_bytes": "136864328",
        "blocksize": "16384",
        "io_bytes": "8219934720",
        "iops": "8351.421103",
        "latency": "15321030.86797",
        "number_of_jobs": "1",
        "runtime_seconds": "60",
        "std_deviation": "29873638.130586997",
        "total_ios": "501578"
    },
    "16": {
        "bandwidth_bytes": "98732686",
        "blocksize": "16384",
        "io_bytes": "5924356096",
        "iops": "6025.914939",
        "latency": "2650963.134466",
        "number_of_jobs": "1",
        "runtime_seconds": "60",
        "std_deviation": "1022377.4367440003",
        "total_ios": "361579"
    },
    "192": {
        "bandwidth_bytes": "181651970",
        "blocksize": "16384",
        "io_bytes": "10904567808",
        "iops": "11083.974679",
        "latency": "17315255.432074",
        "number_of_jobs": "1",
        "runtime_seconds": "60",
        "std_deviation": "16423843.200993996",
        "total_ios": "665371"
    },
    "2": {
        "bandwidth_bytes": "54497463",
        "blocksize": "16384",
        "io_bytes": "3269902336",
        "iops": "3326.244563",
        "latency": "596764.917331",
        "number_of_jobs": "1",
        "runtime_seconds": "60",
        "std_deviation": "208034.66936799994",
        "total_ios": "199578"
    },
    "24": {
        "bandwidth_bytes": "102238016",
        "blocksize": "16384",
        "io_bytes": "6134792192",
        "iops": "6239.730022",
        "latency": "3842132.421343",
        "number_of_jobs": "1",
        "runtime_seconds": "60",
        "std_deviation": "1659564.5118650002",
        "total_ios": "374415"
    },
    "32": {
        "bandwidth_bytes": "105522614",
        "blocksize": "16384",
        "io_bytes": "6331990016",
        "iops": "6440.072659",
        "latency": "4964604.81235",
        "number_of_jobs": "1",
        "runtime_seconds": "60",
        "std_deviation": "2133917.885223",
        "total_ios": "386443"
    },
    "4": {
        "bandwidth_bytes": "84166208",
        "blocksize": "16384",
        "io_bytes": "5050056704",
        "iops": "5137.047716",
        "latency": "774533.624415",
        "number_of_jobs": "1",
        "runtime_seconds": "60",
        "std_deviation": "360443.21096700005",
        "total_ios": "308228"
    },
    "64": {
        "bandwidth_bytes": "118109000",
        "blocksize": "16384",
        "io_bytes": "7088193536",
        "iops": "7207.751525",
        "latency": "8874916.489986",
        "number_of_jobs": "1",
        "runtime_seconds": "60",
        "std_deviation": "4649474.057257999",
        "total_ios": "432566"
    },
    "8": {
        "bandwidth_bytes": "92622396",
        "blocksize": "16384",
        "io_bytes": "5557436416",
        "iops": "5653.105782",
        "latency": "1410950.261094",
        "number_of_jobs": "1",
        "runtime_seconds": "60",
        "std_deviation": "510387.93067199946",
        "total_ios": "339192"
    },
    "96": {
        "bandwidth_bytes": "137461315",
        "blocksize": "16384",
        "io_bytes": "8250015744",
        "iops": "8388.389956",
        "latency": "11439916.876394",
        "number_of_jobs": "1",
        "runtime_seconds": "60",
        "std_deviation": "6907355.474714999",
        "total_ios": "503446"
    },
    "latency_at_max_bandwidth": "17.315255432074",
    "latency_at_max_iops": "17.315255432074",
    "maximum_bandwidth": "181651970.0",
    "maximum_iops": "11083.974679"
}