{
    "12": {
        "bandwidth_bytes": "272183089.0",
        "blocksize": "4096",
        "io_bytes": "24496750592.0",
        "iops": "66450.95054600001",
        "latency": "177193.84543243545",
        "number_of_jobs": "1",
        "runtime_seconds": "90",
        "std_deviation": "54349.12960973035",
        "total_ios": "5980652"
    },
    "128": {
        "bandwidth_bytes": "883754943.0",
        "blocksize": "4096",
        "io_bytes": "79538884608.0",
        "iops": "215759.241837",
        "latency": "588299.849277422",
        "number_of_jobs": "1",
        "runtime_seconds": "90",
        "std_deviation": "426419.3861014528",
        "total_ios": "19418561"
    },
    "16": {
        "bandwidth_bytes": "318620286.0",
        "blocksize": "4096",
        "io_bytes": "28676145152.0",
        "iops": "77788.157911",
        "latency": "201901.9454208899",
        "number_of_jobs": "1",
        "runtime_seconds": "90",
        "std_deviation": "49439.631274104424",
        "total_ios": "7001012"
    },
    "192": {
        "bandwidth_bytes": "905819088.0",
        "blocksize": "4096",
        "io_bytes": "81525358592.0",
        "iops": "221145.28426300004",
        "latency": "863184.5603860529",
        "number_of_jobs": "1",
        "runtime_seconds": "90",
        "std_deviation": "752531.0441590173",
        "total_ios": "19903476"
    },
    "2": {
        "bandwidth_bytes": "61611256.0",
        "blocksize": "4096",
        "io_bytes": "5545074688.0",
        "iops": "15041.810646",
        "latency": "129606.01596660414",
        "number_of_jobs": "1",
        "runtime_seconds": "90",
        "std_deviation": "83214.30525990052",
        "total_ios": "1353778"
    },
    "24": {
        "bandwidth_bytes": "422562731.0",
        "blocksize": "4096",
        "io_bytes": "38031069184.0",
        "iops": "103164.63150000002",
        "latency": "228714.29205325845",
        "number_of_jobs": "1",
        "runtime_seconds": "90",
        "std_deviation": "50226.35250126181",
        "total_ios": "9284920"
    },
    "288": {
        "bandwidth_bytes": "921889847.0",
        "blocksize": "4096",
        "io_bytes": "82972565504.0",
        "iops": "225067.74322700003",
        "latency": "1274513.02448098",
        "number_of_jobs": "1",
        "runtime_seconds": "90",
        "std_deviation": "1223112.3235866574",
        "total_ios": "20256702"
    },
    "32": {
        "bandwidth_bytes": "521253892.0",
        "blocksize": "4096",
        "io_bytes": "46913372160.0",
        "iops": "127259.05267900001",
        "latency": "247301.1995909113",
        "number_of_jobs": "1",
        "runtime_seconds": "90",
        "std_deviation": "55003.266581918324",
        "total_ios": "11453442"
    },
    "384": {
        "bandwidth_bytes": "924553938.0",
        "blocksize": "4096",
        "io_bytes": "83212685312.0",
        "iops": "225717.078172",
        "latency": "1696261.5638246462",
        "number_of_jobs": "1",
        "runtime_seconds": "90",
        "std_deviation": "1749130.053251329",
        "total_ios": "20315228"
    },
    "4": {
        "bandwidth_bytes": "117394012.0",
        "blocksize": "4096",
        "io_bytes": "10565578752.0",
        "iops": "28660.648215",
        "latency": "136244.46594980438",
        "number_of_jobs": "1",
        "runtime_seconds": "90",
        "std_deviation": "68874.01508243711",
        "total_ios": "2579487"
    },
    "64": {
        "bandwidth_bytes": "768735056.0",
        "blocksize": "4096",
        "io_bytes": "69186924544.0",
        "iops": "187678.92579",
        "latency": "336379.8319984332",
        "number_of_jobs": "1",
        "runtime_seconds": "90",
        "std_deviation": "142453.75696299577",
        "total_ios": "16891291"
    },
    "8": {
        "bandwidth_bytes": "210131563.0",
        "blocksize": "4096",
        "io_bytes": "18912051200.0",
        "iops": "51301.652202000005",
        "latency": "152802.7820494825",
        "number_of_jobs": "1",
        "runtime_seconds": "90",
        "std_deviation": "57035.02058551195",
        "total_ios": "4617200"
    },
    "96": {
        "bandwidth_bytes": "850268949.0",
        "blocksize": "4096",
        "io_bytes": "76525109248.0",
        "iops": "207584.305702",
        "latency": "457608.09102978697",
        "number_of_jobs": "1",
        "runtime_seconds": "90",
        "std_deviation": "274988.1866785059",
        "total_ios": "18682808"
    },
    "latency_at_max_bandwidth": "1.696261563824646",
    "latency_at_max_iops": "1.696261563824646",
    "maximum_bandwidth": "924553938.0",
    "maximum_iops": "225717.078172"
}