{
    "1": {
        "bandwidth_bytes": "17762060",
        "blocksize": "16384",
        "io_bytes": "1598603264",
        "iops": "1084.110176",
        "latency": "912919.7178259887",
        "number_of_jobs": "1",
        "percentage_reads": "70",
        "percentage_writes": "30",
        "runtime_seconds": "90",
        "std_deviation": "3391899.939951647",
        "total_ios": "97571"
    },
    "128": {
        "bandwidth_bytes": "1156159679.0",
        "blocksize": "16384",
        "io_bytes": "104056832000.0",
        "iops": "70565.132117",
        "latency": "1801968.4214606027",
        "number_of_jobs": "1",
        "percentage_reads": "70",
        "percentage_writes": "30",
        "runtime_seconds": "90",
        "std_deviation": "1539085.4167343797",
        "total_ios": "6351012"
    },
    "16": {
        "bandwidth_bytes": "497331144.0",
        "blocksize": "16384",
        "io_bytes": "44760301568.0",
        "iops": "30354.684951000003",
        "latency": "518686.52802791726",
        "number_of_jobs": "1",
        "percentage_reads": "70",
        "percentage_writes": "30",
        "runtime_seconds": "90",
        "std_deviation": "615993.244160131",
        "total_ios": "2731952"
    },
    "2": {
        "bandwidth_bytes": "53031687.0",
        "blocksize": "16384",
        "io_bytes": "4772904960.0",
        "iops": "3236.7973700000002",
        "latency": "611941.9328526672",
        "number_of_jobs": "1",
        "percentage_reads": "70",
        "percentage_writes": "30",
        "runtime_seconds": "90",
        "std_deviation": "3008039.4806882753",
        "total_ios": "291315"
    },
    "24": {
        "bandwidth_bytes": "705935918.0",
        "blocksize": "16384",
        "io_bytes": "63534940160.0",
        "iops": "43086.821255999996",
        "latency": "548193.4563740584",
        "number_of_jobs": "1",
        "percentage_reads": "70",
        "percentage_writes": "30",
        "runtime_seconds": "90",
        "std_deviation": "577367.5490605913",
        "total_ios": "3877857"
    },
    "256": {
        "bandwidth_bytes": "1183684102.0",
        "blocksize": "16384",
        "io_bytes": "106544807936.0",
        "iops": "72243.65665799999",
        "latency": "3531625.5324471463",
        "number_of_jobs": "1",
        "percentage_reads": "70",
        "percentage_writes": "30",
        "runtime_seconds": "90",
        "std_deviation": "6850554.309855278",
        "total_ios": "6502737"
    },
    "3": {
        "bandwidth_bytes": "117399701.0",
        "blocksize": "16384",
        "io_bytes": "10566090752.0",
        "iops": "7165.509272",
        "latency": "413711.19923318713",
        "number_of_jobs": "1",
        "percentage_reads": "70",
        "percentage_writes": "30",
        "runtime_seconds": "90",
        "std_deviation": "235758.3095794719",
        "total_ios": "644903"
    },
    "32": {
        "bandwidth_bytes": "816159697.0",
        "blocksize": "16384",
        "io_bytes": "73455190016.0",
        "iops": "49814.246506",
        "latency": "632460.3309062967",
        "number_of_jobs": "1",
        "percentage_reads": "70",
        "percentage_writes": "30",
        "runtime_seconds": "90",
        "std_deviation": "404661.2530426106",
        "total_ios": "4483332"
    },
    "4": {
        "bandwidth_bytes": "172502848.0",
        "blocksize": "16384",
        "io_bytes": "15525429248.0",
        "iops": "10528.73857",
        "latency": "374866.37098779797",
        "number_of_jobs": "1",
        "percentage_reads": "70",
        "percentage_writes": "30",
        "runtime_seconds": "90",
        "std_deviation": "637549.9226665415",
        "total_ios": "947597"
    },
    "64": {
        "bandwidth_bytes": "1031327857.0",
        "blocksize": "16384",
        "io_bytes": "92820733952.0",
        "iops": "62946.72467199998",
        "latency": "1005086.7832634588",
        "number_of_jobs": "1",
        "percentage_reads": "70",
        "percentage_writes": "30",
        "runtime_seconds": "90",
        "std_deviation": "791815.6438088154",
        "total_ios": "5665280"
    },
    "8": {
        "bandwidth_bytes": "315331511.0",
        "blocksize": "16384",
        "io_bytes": "28380151808.0",
        "iops": "19246.297264999997",
        "latency": "409427.2962147029",
        "number_of_jobs": "1",
        "percentage_reads": "70",
        "percentage_writes": "30",
        "runtime_seconds": "90",
        "std_deviation": "200284.69775594154",
        "total_ios": "1732186"
    },
    "latency_at_max_bandwidth": "3.5316255324471464",
    "latency_at_max_iops": "3.5316255324471464",
    "maximum_bandwidth": "1183684102.0",
    "maximum_iops": "72243.65665799999"
}