{
    "12": {
        "bandwidth_bytes": "197913170.0",
        "blocksize": "8192",
        "io_bytes": "17812365312.0",
        "iops": "24159.323262",
        "latency": "408442.0610619899",
        "number_of_jobs": "1",
        "runtime_seconds": "90",
        "std_deviation": "92750.12433518263",
        "total_ios": "2174361"
    },
    "128": {
        "bandwidth_bytes": "278996926.0",
        "blocksize": "8192",
        "io_bytes": "25110282240.0",
        "iops": "34056.464902",
        "latency": "2343645.9154771413",
        "number_of_jobs": "1",
        "runtime_seconds": "90",
        "std_deviation": "1080075.2147138212",
        "total_ios": "3065150"
    },
    "16": {
        "bandwidth_bytes": "170406265.0",
        "blocksize": "8192",
        "io_bytes": "15336734720.0",
        "iops": "20801.546650000004",
        "latency": "474208.28287766787",
        "number_of_jobs": "1",
        "runtime_seconds": "90",
        "std_deviation": "111880.20241664608",
        "total_ios": "1872160"
    },
    "192": {
        "bandwidth_bytes": "293503216.0",
        "blocksize": "8192",
        "io_bytes": "26416168960.0",
        "iops": "35826.807885",
        "latency": "3344240.026847046",
        "number_of_jobs": "1",
        "runtime_seconds": "90",
        "std_deviation": "1578778.946704016",
        "total_ios": "3224520"
    },
    "2": {
        "bandwidth_bytes": "53443103.0",
        "blocksize": "8192",
        "io_bytes": "4809932800.0",
        "iops": "6523.816402",
        "latency": "303096.8395303728",
        "number_of_jobs": "1",
        "runtime_seconds": "90",
        "std_deviation": "90955.9230885662",
        "total_ios": "587150"
    },
    "24": {
        "bandwidth_bytes": "234183008.0",
        "blocksize": "8192",
        "io_bytes": "21076705280.0",
        "iops": "28586.693482",
        "latency": "623604.3699961988",
        "number_of_jobs": "1",
        "runtime_seconds": "90",
        "std_deviation": "189712.38860027652",
        "total_ios": "2572831"
    },
    "288": {
        "bandwidth_bytes": "298529327.0",
        "blocksize": "8192",
        "io_bytes": "26869276672.0",
        "iops": "36439.680095",
        "latency": "4934634.116745102",
        "number_of_jobs": "1",
        "runtime_seconds": "90",
        "std_deviation": "2557864.0730973785",
        "total_ios": "3279771"
    },
    "32": {
        "bandwidth_bytes": "219499464.0",
        "blocksize": "8192",
        "io_bytes": "19755171840.0",
        "iops": "26794.246730000003",
        "latency": "739965.2192728387",
        "number_of_jobs": "1",
        "runtime_seconds": "90",
        "std_deviation": "240195.3418824558",
        "total_ios": "2411509"
    },
    "4": {
        "bandwidth_bytes": "108146577.0",
        "blocksize": "8192",
        "io_bytes": "9733300224.0",
        "iops": "13201.486649999999",
        "latency": "299508.9971006122",
        "number_of_jobs": "1",
        "runtime_seconds": "90",
        "std_deviation": "72055.79939442688",
        "total_ios": "1188147"
    },
    "64": {
        "bandwidth_bytes": "257923197.0",
        "blocksize": "8192",
        "io_bytes": "23213424640.0",
        "iops": "31484.42143",
        "latency": "1264477.2783092642",
        "number_of_jobs": "1",
        "runtime_seconds": "90",
        "std_deviation": "510928.97100144025",
        "total_ios": "2833639"
    },
    "8": {
        "bandwidth_bytes": "183049203.0",
        "blocksize": "8192",
        "io_bytes": "16474611712.0",
        "iops": "22344.873946",
        "latency": "353636.80195441295",
        "number_of_jobs": "1",
        "runtime_seconds": "90",
        "std_deviation": "82317.73070697192",
        "total_ios": "2011061"
    },
    "96": {
        "bandwidth_bytes": "270701408.0",
        "blocksize": "8192",
        "io_bytes": "24363614208.0",
        "iops": "33044.050589000006",
        "latency": "1810158.7282875334",
        "number_of_jobs": "1",
        "runtime_seconds": "90",
        "std_deviation": "813342.5310068317",
        "total_ios": "2974024"
    },
    "latency_at_max_bandwidth": "4.934634116745102",
    "latency_at_max_iops": "4.934634116745102",
    "maximum_bandwidth": "298529327.0",
    "maximum_iops": "36439.680095"
}