{
    "128": {
        "bandwidth_bytes": "600734486.0",
        "blocksize": "1048576",
        "io_bytes": "54171533312.0",
        "iops": "571.574317",
        "latency": "222914379.54620308",
        "number_of_jobs": "1",
        "runtime_seconds": "90",
        "std_deviation": "84422959.93792605",
        "total_ios": "51542"
    },
    "16": {
        "bandwidth_bytes": "185833096.0",
        "blocksize": "1048576",
        "io_bytes": "16734224384.0",
        "iops": "177.135416",
        "latency": "89751979.25282042",
        "number_of_jobs": "1",
        "runtime_seconds": "90",
        "std_deviation": "24354085.196537163",
        "total_ios": "15951"
    },
    "160": {
        "bandwidth_bytes": "441504453.0",
        "blocksize": "1048576",
        "io_bytes": "39798702080.0",
        "iops": "419.365259",
        "latency": "380644980.32438105",
        "number_of_jobs": "1",
        "runtime_seconds": "90",
        "std_deviation": "91135292.55985259",
        "total_ios": "37803"
    },
    "2": {
        "bandwidth_bytes": "57189972.0",
        "blocksize": "1048576",
        "io_bytes": "5149556736.0",
        "iops": "54.540608",
        "latency": "36480708.25351251",
        "number_of_jobs": "1",
        "runtime_seconds": "90",
        "std_deviation": "24216308.750657037",
        "total_ios": "4911"
    },
    "32": {
        "bandwidth_bytes": "260480979.0",
        "blocksize": "1048576",
        "io_bytes": "23450353664.0",
        "iops": "248.13633200000004",
        "latency": "128326924.85699357",
        "number_of_jobs": "1",
        "runtime_seconds": "90",
        "std_deviation": "26802228.792775102",
        "total_ios": "22339"
    },
    "4": {
        "bandwidth_bytes": "98184438.0",
        "blocksize": "1048576",
        "io_bytes": "8839495680.0",
        "iops": "93.63597899999999",
        "latency": "42440340.048754476",
        "number_of_jobs": "1",
        "runtime_seconds": "90",
        "std_deviation": "23246396.627201512",
        "total_ios": "8430"
    },
    "48": {
        "bandwidth_bytes": "366755867.0",
        "blocksize": "1048576",
        "io_bytes": "33015463936.0",
        "iops": "349.31021",
        "latency": "136712454.85896966",
        "number_of_jobs": "1",
        "runtime_seconds": "90",
        "std_deviation": "46260762.59314116",
        "total_ios": "31445"
    },
    "6": {
        "bandwidth_bytes": "141399746.0",
        "blocksize": "1048576",
        "io_bytes": "12728664064.0",
        "iops": "134.849308",
        "latency": "44101496.19729797",
        "number_of_jobs": "1",
        "runtime_seconds": "90",
        "std_deviation": "23595109.134489093",
        "total_ios": "12139"
    },
    "64": {
        "bandwidth_bytes": "435715347.0",
        "blocksize": "1048576",
        "io_bytes": "39260782592.0",
        "iops": "414.90905300000003",
        "latency": "153485593.81155014",
        "number_of_jobs": "1",
        "runtime_seconds": "90",
        "std_deviation": "55652704.765778296",
        "total_ios": "37386"
    },
    "8": {
        "bandwidth_bytes": "154111042.0",
        "blocksize": "1048576",
        "io_bytes": "13878951936.0",
        "iops": "146.971748",
        "latency": "53943913.783091664",
        "number_of_jobs": "1",
        "runtime_seconds": "90",
        "std_deviation": "25439343.961377725",
        "total_ios": "13236"
    },
    "96": {
        "bandwidth_bytes": "505531985.0",
        "blocksize": "1048576",
        "io_bytes": "45527072768.0",
        "iops": "481.135723",
        "latency": "198819140.81770736",
        "number_of_jobs": "1",
        "runtime_seconds": "90",
        "std_deviation": "81972220.37194563",
        "total_ios": "43330"
    },
    "latency_at_max_bandwidth": "222.91437954620307",
    "latency_at_max_iops": "222.91437954620307",
    "maximum_bandwidth": "600734486.0",
    "maximum_iops": "571.574317"
}